auran/__init__.py
auran/brain.py
auran/cache.py
auran/command_line.py
auran/config.py
auran/cryo.py
auran/dashboard.py
auran/device.py
auran/organism.py
auran/recorder.py
auran/training.py
auran/world.py
auran/xp.py
auran/ann/__init__.py
auran/ann/combine.py
auran/ann/common.py
auran/ann/container.py
auran/ann/conv.py
auran/ann/distributions.py
auran/ann/dropout.py
auran/ann/image.py
auran/ann/io.py
auran/ann/linear.py
auran/ann/nonlinear.py
auran/ann/norm.py
auran/ann/pool.py
auran/ann/utils.py
auran-0.1.1.dist-info/LICENSE
auran-0.1.1.dist-info/METADATA
auran-0.1.1.dist-info/WHEEL
auran-0.1.1.dist-info/entry_points.txt
auran-0.1.1.dist-info/top_level.txt
auran-0.1.1.dist-info/RECORD
