Metadata-Version: 2.1
Name: auran
Version: 0.1.1
Summary: auran is a python package built on top of pytorch to ease creation of artificial neural networks.
Home-page: UNKNOWN
Author: Francois Lagunas
Author-email: francois.lagunas@m4x.org
License: MIT
Platform: UNKNOWN
Classifier: Development Status :: 3 - Alpha
Classifier: License :: OSI Approved :: MIT License
Classifier: Programming Language :: Python :: 3.0
Classifier: Topic :: Scientific/Engineering :: Artificial Intelligence
Requires-Dist: click
